mavometer/MessageStats.py
mavometer/MessageTableView.py
mavometer/__init__.py
mavometer-0.1.0.data/scripts/mavometer
mavometer-0.1.0.dist-info/LICENSE
mavometer-0.1.0.dist-info/METADATA
mavometer-0.1.0.dist-info/WHEEL
mavometer-0.1.0.dist-info/top_level.txt
mavometer-0.1.0.dist-info/RECORD
