Metadata-Version: 2.1
Name: mavometer
Version: 0.1.0
Summary: Application to monitor bandwidth and message composition of a MAVLink stream
Home-page: https://github.com/langrind/mavometer
Author: Nik Langrind
Author-email: langrind@gmail.com
License: MIT
Platform: UNKNOWN
Classifier: Programming Language :: Python :: 3
Classifier: License :: OSI Approved :: MIT License
Classifier: Operating System :: OS Independent
Requires-Python: >=3.6
Requires-Dist: pymavlink
Requires-Dist: uqtie (>=0.1.1)
